setup.py
pd2gs/__init__.py
pd2gs/pd2gs.py
pd2gs.egg-info/PKG-INFO
pd2gs.egg-info/SOURCES.txt
pd2gs.egg-info/dependency_links.txt
pd2gs.egg-info/not-zip-safe
pd2gs.egg-info/requires.txt
pd2gs.egg-info/top_level.txt