Metadata-Version: 1.0
Name: pd2gs
Version: 0.1
Summary: Simple tool to export pandas dataframes to google sheets.
Home-page: https://github.com/Ozzerov/pd2gs
Author: Alex Ozerov
Author-email: ozerov@yandex.ru
License: MIT
Platform: UNKNOWN
